genty/__init__.py
genty/genty.py
genty/genty_args.py
genty/genty_dataset.py
genty/genty_repeat.py
genty/private/__init__.py
genty-1.3.2.dist-info/DESCRIPTION.rst
genty-1.3.2.dist-info/LICENSE.txt
genty-1.3.2.dist-info/METADATA
genty-1.3.2.dist-info/RECORD
genty-1.3.2.dist-info/WHEEL
genty-1.3.2.dist-info/metadata.json
genty-1.3.2.dist-info/top_level.txt
