Metadata-Version: 2.0
Name: genty
Version: 1.3.2
Summary: Allows you to run a test with multiple data sets
Home-page: https://github.com/box/genty
Author: Box
Author-email: oss@box.com
License: Apache Software License, Version 2.0, http://www.apache.org/licenses/LICENSE-2.0
Keywords: genty,tests,generative,unittest
Platform: UNKNOWN
Classifier: Development Status :: 4 - Beta
Classifier: Intended Audience :: Developers
Classifier: License :: OSI Approved :: Apache Software License
Classifier: Topic :: Software Development
Classifier: Programming Language :: Python
Classifier: Programming Language :: Python :: 2.6
Classifier: Programming Language :: Python :: 2.7
Classifier: Programming Language :: Python :: 3.3
Classifier: Programming Language :: Python :: 3.4
Classifier: Programming Language :: Python :: 3.5
Classifier: Programming Language :: Python :: Implementation :: CPython
Classifier: Programming Language :: Python :: Implementation :: PyPy
Classifier: Operating System :: OS Independent
Classifier: Operating System :: POSIX
Classifier: Operating System :: Microsoft :: Windows
Classifier: Operating System :: MacOS :: MacOS X
Requires-Dist: six
Requires-Dist: ordereddict; python_version=="2.6"
